barely_json/__init__.py
barely_json-1.0.0.dist-info/LICENSE
barely_json-1.0.0.dist-info/METADATA
barely_json-1.0.0.dist-info/WHEEL
barely_json-1.0.0.dist-info/top_level.txt
barely_json-1.0.0.dist-info/RECORD
