Metadata-Version: 2.1
Name: barely-json
Version: 1.0.0
Summary: Parse invalid, malformed and barely JSON-esque data
Home-page: https://github.com/torfsen/barely_json
Author: Florian Brucker
Author-email: mail@florianbrucker.de
License: MIT
Keywords: json
Classifier: Development Status :: 5 - Production/Stable
Classifier: Intended Audience :: Developers
Classifier: License :: OSI Approved :: MIT License
Classifier: Programming Language :: Python :: 3
Classifier: Programming Language :: Python :: 3.7
Classifier: Programming Language :: Python :: 3.8
Classifier: Programming Language :: Python :: 3.9
Classifier: Programming Language :: Python :: 3.10
Classifier: Programming Language :: Python :: 3.11
Classifier: Topic :: Software Development :: Libraries :: Python Modules
License-File: LICENSE
Requires-Dist: pyparsing (>=3.1.0)
